pytorch_normalizers/__init__.py
pytorch_normalizers/quantile_norm.py
pytorch_normalizers/smooth_buckets.py
pytorch_normalizers-0.1.3.dist-info/licenses/LICENSE
pytorch_normalizers-0.1.3.dist-info/METADATA
pytorch_normalizers-0.1.3.dist-info/WHEEL
pytorch_normalizers-0.1.3.dist-info/top_level.txt
pytorch_normalizers-0.1.3.dist-info/RECORD
