Metadata-Version: 2.4
Name: pytorch-normalizers
Version: 0.1.3
Summary: PyTorch normalization layers for numerical features, including SmoothBuckets and QuantileNorm
Author-email: Alon Rozental <alonzorz@gmail.com>
License: MIT License
Project-URL: Homepage, https://github.com/yourusername/pytorch_normalizers
Project-URL: Repository, https://github.com/yourusername/pytorch_normalizers.git
Project-URL: Issues, https://github.com/yourusername/pytorch_normalizers/issues
Classifier: Programming Language :: Python :: 3
Classifier: License :: OSI Approved :: MIT License
Classifier: Operating System :: OS Independent
Classifier: Topic :: Scientific/Engineering :: Artificial Intelligence
Requires-Python: >=3.8
License-File: LICENSE
Requires-Dist: torch>=2.0.0
Requires-Dist: numpy>=1.20.0
Provides-Extra: test
Requires-Dist: pandas>=1.0.0; extra == "test"
Requires-Dist: catboost>=1.0.0; extra == "test"
Requires-Dist: pytest>=7.0.0; extra == "test"
Dynamic: license-file
